[
  {
    "title_en": "Inverted World",
    "artist": "ARForest",
    "length": 128,
    "bpm_min": 180,
    "bpm_max": 180,
    "level_easy": 4,
    "level_hard": 6,
    "level_master": 8,
    "level_supreme": 10
  },
  {
    "title_en": "翠杜",
    "artist": "隣の庭は青い(庭師+Aoi)",
    "length": 141,
    "bpm_min": 180,
    "bpm_max": 180,
    "level_easy": 6,
    "level_hard": 8,
    "level_master": 11,
    "level_supreme": 12
  },
  {
    "title_en": "The Promised Land",
    "artist": "Iris feat. LynH",
    "length": 141,
    "bpm_min": 140,
    "bpm_max": 140,
    "level_easy": 4,
    "level_hard": 6,
    "level_master": 9,
    "level_supreme": null
  },
  {
    "title_en": "Alfheim's faith",
    "artist": "Kagetora.",
    "length": 132,
    "bpm_min": 200,
    "bpm_max": 200,
    "level_easy": 6,
    "level_hard": 8,
    "level_master": 11,
    "level_supreme": null
  },
  {
    "title_en": "Heaven's Cage",
    "artist": "ETIA.",
    "length": 152,
    "bpm_min": 190,
    "bpm_max": 190,
    "level_easy": 5,
    "level_hard": 7,
    "level_master": 10,
    "level_supreme": 11
  },
  {
    "title_en": "Broomstick adventure!",
    "artist": "しーけー",
    "length": 131,
    "bpm_min": 180,
    "bpm_max": 180,
    "level_easy": 7,
    "level_hard": 9,
    "level_master": 11,
    "level_supreme": null
  }
]